README.txt
setup.py
src/pytoolbelt/__init__.py
src/pytoolbelt.egg-info/PKG-INFO
src/pytoolbelt.egg-info/SOURCES.txt
src/pytoolbelt.egg-info/dependency_links.txt
src/pytoolbelt.egg-info/namespace_packages.txt
src/pytoolbelt.egg-info/not-zip-safe
src/pytoolbelt.egg-info/top_level.txt
src/pytoolbelt/asset_mgmt/__init__.py
src/pytoolbelt/asset_mgmt/filters.py
src/pytoolbelt/asset_mgmt/handler.py
src/pytoolbelt/asset_mgmt/engines/__init__.py
src/pytoolbelt/asset_mgmt/engines/default.py
src/pytoolbelt/tools/__init__.py
src/pytoolbelt/tools/common.py
src/pytoolbelt/tools/enum.py
src/pytoolbelt/wtforms/__init__.py
src/pytoolbelt/wtforms/fields.py